LICENSE.txt
README.md
setup.cfg
setup.py
py_data_structure/__init__.py
py_data_structure/main.py
py_data_structure.egg-info/PKG-INFO
py_data_structure.egg-info/SOURCES.txt
py_data_structure.egg-info/dependency_links.txt
py_data_structure.egg-info/top_level.txt