Metadata-Version: 2.1
Name: py-data-structure
Version: 0.1.2
Summary: A package that allows you to implement C++ data structures in Python.
Home-page: https://github.com/tinyCodersDen/py-data-structure
Author: Vihan
Author-email: vihan.raval1@gmail.com
License: MIT
Download-URL: https://github.com/tinyCodersDen/py-data-structure/archive/refs/tags/v_0.1.2.tar.gz
Keywords: Data,structures,data structures,stacks,queues
Platform: UNKNOWN
Classifier: Development Status :: 3 - Alpha
Classifier: License :: OSI Approved :: MIT License
Classifier: Programming Language :: Python :: 3
Classifier: Programming Language :: Python :: 3.4
Classifier: Programming Language :: Python :: 3.5
Classifier: Programming Language :: Python :: 3.6
